cli/main.py
datakitcli-0.2.1.dist-info/LICENSE
datakitcli-0.2.1.dist-info/METADATA
datakitcli-0.2.1.dist-info/WHEEL
datakitcli-0.2.1.dist-info/entry_points.txt
datakitcli-0.2.1.dist-info/top_level.txt
datakitcli-0.2.1.dist-info/RECORD
